{
  "straitStatus": "effectively_closed",
  "blockadeDay": 14,
  "blockadeStartDate": "2026-03-03",
  "lastUpdated": "2026-03-13T23:45:00Z",
  "statistics": {
    "normalDailyBarrels": 15000000,
    "currentDailyBarrels": 0,
    "globalOilSharePercent": 20,
    "vesselsAnchored": 340,
    "vesselsTransitLast24h": 0,
    "containershipsTrapped": 180,
    "tankersAtAnchor": 160,
    "vlccDailyRate": 400000,
    "vesselsDamaged": 14,
    "vesselsSunk": 2,
    "insuranceStatus": "withdrawn",
    "naviesPresent": [
      "US 5th Fleet",
      "Royal Navy",
      "IRGC Navy",
      "French Navy"
    ]
  },
  "timeline": [
    {
      "date": "2026-03-01",
      "event": "Iran begins deploying naval mines in Strait of Hormuz",
      "status": "partially_blocked",
      "barrels": 8000000
    },
    {
      "date": "2026-03-02",
      "event": "IRGC deploys anti-ship missiles along Iranian coastline",
      "status": "partially_blocked",
      "barrels": 3000000
    },
    {
      "date": "2026-03-03",
      "event": "Full blockade declared. War-risk insurance pulled by Lloyd's of London.",
      "status": "blocked",
      "barrels": 500000
    },
    {
      "date": "2026-03-04",
      "event": "4 commercial vessels struck by mines/missiles. 150+ vessels at anchor.",
      "status": "blocked",
      "barrels": 0
    },
    {
      "date": "2026-03-05",
      "event": "1 oil tanker sunk. All major shipping companies halt Persian Gulf operations.",
      "status": "blocked",
      "barrels": 0
    },
    {
      "date": "2026-03-06",
      "event": "US Navy minesweeping operations begin. No commercial transit.",
      "status": "blocked",
      "barrels": 0
    },
    {
      "date": "2026-03-07",
      "event": "Only 9 vessels total crossed strait this week. Dry bulk transits down 91%. ~280 bulkers trapped. IRGC drones hit tankers Prima and Louise P.",
      "status": "blocked",
      "barrels": 0
    },
    {
      "date": "2026-03-08",
      "event": "Tehran oil depots bombed — fuel distribution halted. Brent crude +27% for the week. US Navy still not escorting. IRGC vows 6+ months capability.",
      "status": "blocked",
      "barrels": 0
    },
    {
      "date": "2026-03-09",
      "event": "Strait effectively closed — zero transits for 48+ hours. 310+ vessels at anchor. 8 commercial vessels damaged total, 2 sunk. Brent crude hits $119.50 intraday before settling at $103.47. US minesweeping makes minimal progress. IRGC deploys additional fast attack boats.",
      "status": "effectively_closed",
      "barrels": 0
    },
    {
      "date": "2026-03-10",
      "event": "Day 11 — Only 13 vessels/day average; March 8 saw only 2 outbound transits. 170+ containerships trapped, 150+ tankers at anchor. Insurance withdrawn by all major providers. VLCC charter rates surge from $50K to $400K/day. Brent crude holds above $110.",
      "status": "effectively_closed",
      "barrels": 900000
    },
    {
      "date": "2026-03-11",
      "event": "Day 12 — 3 more ships attacked (total 14 damaged/sunk since war began). Shipping traffic down 95% from pre-war. 330+ vessels at anchor. IEA approves record 400M barrel emergency reserve release. Brent rebounds +3.4% to $90.77. Iran deploys Khoramshahr super-heavy missiles.",
      "status": "effectively_closed",
      "barrels": 0
    },
    {
      "date": "2026-03-12",
      "event": "Day 13 — Two more tankers hit in Iraqi waters (total 16 damaged/sunk). 280+ bulk carriers stranded. Dry bulk trade down 91%. Brent crosses $100. IEA 400M barrel release across 32 countries (US contributing 172M from SPR) fails to contain surge. Mojtaba Khamenei vows Hormuz stays closed.",
      "status": "effectively_closed",
      "barrels": 0
    },
    {
      "date": "2026-03-13",
      "event": "No commercial transits in either direction for 24 hours (Bloomberg). Iran considering yuan-only access. 2 Indian LPG carriers allowed under Indian Navy escort — rare exception. Hegseth: 'no clear evidence' of new mines but strait 'won't remain contested.'",
      "status": "effectively_closed",
      "barrels": 0
    }
  ],
  "impactedGoods": [
    {
      "commodity": "Crude Oil",
      "normalFlow": "15M bbl/day",
      "currentFlow": "0 bbl/day",
      "priceImpact": "+24.6% (Brent $100.46, WTI $95.73)",
      "detail": "20% of global supply cut off. Brent past $100/barrel for first time since 2022. IEA record 400M barrel release across 32 countries (US contributing 172M from SPR) fails to contain surge. 16 ships now damaged/sunk. 280+ bulk carriers stranded, dry bulk trade down 91%. Traffic down 95%+."
    },
    {
      "commodity": "LNG",
      "normalFlow": "~25% of global",
      "currentFlow": "0 (Qatar shut down)",
      "priceImpact": "+52%",
      "detail": "Qatar's LNG export facilities damaged. 17 Iranian ballistic missiles intercepted over Doha on March 8. European gas prices at record levels."
    },
    {
      "commodity": "Refined Products",
      "normalFlow": "2M bbl/day",
      "currentFlow": "0",
      "priceImpact": "+12%",
      "detail": "Jet fuel, diesel, gasoline exports halted. US gas prices at $3.60/gal (AAA), up 13.2% from pre-war $3.18. California above $5.00/gal. Oil at ~$100/barrel. Treasury waived Russia oil sanctions for 1 month. IEA 400M barrel release ongoing. Gas Prices Relief Act introduced to suspend 18.4c/gal federal gas tax."
    },
    {
      "commodity": "Petrochemicals",
      "normalFlow": "Various",
      "currentFlow": "Minimal",
      "priceImpact": "+28%",
      "detail": "Fertilizer and plastics supply chain severely disrupted. Food commodity prices surging 30-50% above pre-war levels."
    }
  ]
}