{
  "lastUpdated": "2026-04-24T00:07:00Z",
  "categories": [
    {
      "id": "us-left",
      "label": "US Left-Leaning Media",
      "color": "#3b82f6",
      "icon": "📰",
      "outlets": [
        {
          "name": "CNN",
          "headline": "Trump declines to give timeline on ending war with Iran: 'Don't rush me'",
          "timestamp": "2026-04-23T22:00:00Z",
          "url": "https://www.cnn.com/2026/04/23/world/live-news/iran-war-trump-blockade-israel-lebanon",
          "summary": "CNN leads with Trump refusing to set timeline, Lebanon ceasefire extension, Hezbollah rockets at Shtula, and Pentagon casualty count controversy."
        },
        {
          "name": "NBC News",
          "headline": "Trump orders U.S. to attack Iran boats mining Strait of Hormuz",
          "timestamp": "2026-04-23T20:00:00Z",
          "url": "https://www.nbcnews.com/world/iran/live-blog/live-updates-trump-iran-hormuz-blockade-ceasefire-talks-lebanon-israel-rcna341571",
          "summary": "NBC covers Trump's shoot-and-kill order, 7 ships transiting Hormuz in 12 hours, and Lebanon ceasefire extension."
        }
      ]
    },
    {
      "id": "us-right",
      "label": "US Right-Leaning Media",
      "color": "#ef4444",
      "icon": "📺",
      "outlets": [
        {
          "name": "Fox News",
          "headline": "US used roughly half its Patriot interceptors in Iran war — yearslong rebuild looms, CSIS finds",
          "timestamp": "2026-04-23T18:00:00Z",
          "url": "https://www.foxnews.com/politics/us-drains-critical-missile-stockpiles-iran-war-yearslong-rebuild-looms",
          "summary": "Fox leads with CSIS munitions depletion report — 50% Patriot interceptors, 850+ Tomahawks expended. Frames as readiness concern for China deterrence."
        },
        {
          "name": "RedState",
          "headline": "Iran War pushes gas past $4 — US still paying far less than most countries",
          "timestamp": "2026-04-21T14:00:00Z",
          "url": "https://redstate.com/wardclark/2026/04/21/iran-war-drives-4-gas-us-still-now-paying-far-less-than-most-countries-n2201534",
          "summary": "Coverage framing US gas prices as painful but noting Americans pay less than European allies hit harder by the Hormuz blockade."
        }
      ]
    },
    {
      "id": "international",
      "label": "International Media",
      "color": "#8b5cf6",
      "icon": "🌍",
      "outlets": [
        {
          "name": "Al Jazeera",
          "headline": "US to 'shoot and kill' Iranian boats laying mines in Hormuz, Trump says",
          "timestamp": "2026-04-23T18:00:00Z",
          "url": "https://www.aljazeera.com/news/2026/4/23/us-to-shoot-and-kill-iranian-boats-laying-mines-in-hormuz-trump-says",
          "summary": "Al Jazeera leads with Trump's shoot-and-kill order for Hormuz, Iran's coordinated unity statement, and Lebanon ceasefire extension."
        },
        {
          "name": "France 24",
          "headline": "Trump announces three-week extension of Israel-Lebanon ceasefire",
          "timestamp": "2026-04-23T22:00:00Z",
          "url": "https://www.france24.com/en/middle-east/20260423-middle-east-war-live-lebanon-meets-israel-in-washington-to-request-truce-extension",
          "summary": "France 24 covers Lebanon ceasefire extension, UK-France led Hormuz planning conference with 30+ nations."
        }
      ]
    },
    {
      "id": "israeli",
      "label": "Israeli Media",
      "color": "#f59e0b",
      "icon": "✡️",
      "outlets": [
        {
          "name": "Times of Israel",
          "headline": "Trump declares 3-week truce extension as Israel and Lebanon hold talks at White House",
          "timestamp": "2026-04-24T00:00:00Z",
          "url": "https://www.timesofisrael.com/liveblog-april-24-2026/",
          "summary": "ToI covers ceasefire extension, Hezbollah rockets at Shtula, two IDF soldiers indicted for Iran espionage, and Israeli security discussion on 'decision point.'"
        },
        {
          "name": "Haaretz",
          "headline": "Two Air Force soldiers charged with spying for Iran; Hezbollah fires rockets at Israel",
          "timestamp": "2026-04-23T20:00:00Z",
          "url": "https://www.haaretz.com/israel-news/israel-security/2026-04-23/ty-article-live/reports-five-killed-including-three-children-in-israeli-strike-in-north-gaza/0000019d-b7ef-db3c-a1ff-f7efd6dc0000",
          "summary": "Haaretz leads with espionage indictment and Shtula rocket attack. Notes Israeli officials see 'decision point' on Iran nearing."
        }
      ]
    },
    {
      "id": "iranian",
      "label": "Iranian State Media",
      "color": "#10b981",
      "icon": "🇮🇷",
      "outlets": [
        {
          "name": "Press TV",
          "headline": "Military aggression failed, US bullying won't open Strait of Hormuz: Qalibaf",
          "timestamp": "2026-04-22T18:00:00Z",
          "url": "https://www.presstv.ir/Detail/2026/04/22/767376/Iran-Hormuz-reopening-Ghalibaf-US-bullying",
          "summary": "Press TV frames Hormuz closure as Iran's sovereign right, highlights Qalibaf statement that reopening is impossible during US blockade."
        },
        {
          "name": "IRNA",
          "headline": "Iran leaders unite: 'No radicals or moderates — we are all revolutionary'",
          "timestamp": "2026-04-23T15:00:00Z",
          "url": "https://www.aljazeera.com/news/2026/4/23/iran-dismisses-trumps-claim-of-leadership-rift-says-nation-is-one-soul",
          "summary": "Coverage of coordinated unity statement by all senior Iranian officials rejecting Trump's 'fracture' claims."
        }
      ]
    }
  ]
}