{
  "lastUpdated": "2026-04-13T12:02:00Z",
  "categories": [
    {
      "id": "us-left",
      "label": "US Left-Leaning Media",
      "color": "#3b82f6",
      "icon": "📰",
      "outlets": [
        {
          "name": "NPR",
          "headline": "The U.S. military says it will blockade Iranian ports as Iran peace talks collapse",
          "timestamp": "2026-04-13T06:00:00Z",
          "url": "https://www.npr.org/2026/04/12/nx-s1-5782538/u-s-iran-peace-talks-islamabad-collapse",
          "summary": "NPR covers CENTCOM blockade beginning Monday, collapse of Islamabad talks after 21 hours. Trump attacks Pope Leo XIV. Oil surges above $102."
        },
        {
          "name": "PBS NewsHour",
          "headline": "Failed U.S.-Iran negotiations raise questions about fragile ceasefire",
          "timestamp": "2026-04-13T06:00:00Z",
          "url": "https://www.pbs.org/newshour/world/failed-u-s-iran-negotiations-in-pakistan-raise-questions-about-fragile-ceasefire",
          "summary": "PBS covers failed negotiations, CENTCOM blockade of Iranian ports starting Monday, and fact-checks Trump/Hegseth claims of victory."
        }
      ]
    },
    {
      "id": "us-right",
      "label": "US Right-Leaning Media",
      "color": "#ef4444",
      "icon": "📺",
      "outlets": [
        {
          "name": "Fox News",
          "headline": "US blockade of Iranian ports begins Monday, CENTCOM confirms",
          "timestamp": "2026-04-13T06:00:00Z",
          "url": "https://www.foxnews.com/world/gate-tears-risk-iran-threatens-major-new-global-chokepoint-us-moves-hormuz",
          "summary": "Fox covers CENTCOM blockade confirmed for Monday. Iran could deploy Houthis to block Bab al-Mandeb. Steve Forbes op-ed: 'Finish Iran now or accept strategic defeat.'"
        },
        {
          "name": "Fox News (Op-Ed)",
          "headline": "America faces a stark choice: Finish Iran now or accept strategic defeat",
          "timestamp": "2026-04-13T06:00:00Z",
          "url": "https://www.foxnews.com/opinion/steve-forbes-delusions-america-finish-job-iran",
          "summary": "Steve Forbes argues US must finish the job in Iran. Frames blockade as necessary but insufficient — calls for decisive military action."
        }
      ]
    },
    {
      "id": "international",
      "label": "International Media",
      "color": "#8b5cf6",
      "icon": "🌍",
      "outlets": [
        {
          "name": "Al Jazeera",
          "headline": "US military threatens to blockade all Iranian ports starting on Monday",
          "timestamp": "2026-04-13T06:00:00Z",
          "url": "https://www.aljazeera.com/news/2026/4/13/us-military-threatens-to-blockade-all-iranian-ports-starting-on-monday",
          "summary": "Al Jazeera covers CENTCOM blockade confirmed for Monday 10am ET. IRGC threatens 'deadly vortex.' Oil surges above $103. Trump attacks Pope Leo XIV. Allies reject blockade."
        },
        {
          "name": "Al Jazeera",
          "headline": "Oil prices surge past $103 a barrel after US announces blockade of Iran",
          "timestamp": "2026-04-13T06:00:00Z",
          "url": "https://www.aljazeera.com/economy/2026/4/13/oil-prices-surge-past-103-a-barrel-after-us-announces-blockade-of-iran",
          "summary": "Oil surges to $103 intraday. Brent +7.3%, WTI +8.5%. BCA Research warns of 'oil cliff' by April 19 as SPR reserves and sanctions exemptions expire."
        }
      ]
    },
    {
      "id": "israeli",
      "label": "Israeli Media",
      "color": "#f59e0b",
      "icon": "✡️",
      "outlets": [
        {
          "name": "Jerusalem Post",
          "headline": "Netanyahu touts achievements while JD Vance faces stalled Iran talks",
          "timestamp": "2026-04-13T06:00:00Z",
          "url": "https://www.jpost.com/middle-east/article-892754",
          "summary": "JPost covers Netanyahu's victory rhetoric vs failed diplomacy. CENTCOM blockade Monday. 2 IDF soldiers wounded in Lebanon. Netanyahu trial delayed again."
        },
        {
          "name": "Israel Hayom",
          "headline": "Trump declares naval blockade of Strait of Hormuz after Iran nuclear talks collapse",
          "timestamp": "2026-04-13T06:00:00Z",
          "url": "https://www.israelhayom.com/2026/04/13/trump-declares-naval-blockade-of-the-strait-of-hormuz-after-iran-nuclear-talks-collapse/",
          "summary": "Israel Hayom covers Trump blockade declaration. Netanyahu visits troops. Operation Silver Plow continues."
        }
      ]
    },
    {
      "id": "iranian",
      "label": "Iranian State Media",
      "color": "#10b981",
      "icon": "🇮🇷",
      "outlets": [
        {
          "name": "PressTV",
          "headline": "IRGC warns deadly whirlpool for enemies at Hormuz",
          "timestamp": "2026-04-13T06:00:00Z",
          "url": "https://www.presstv.ir/Detail/2026/04/12/766722/IRGC-Any-wrong-move-will-turn-Strait-of-Hormuz-into-deadly-whirlpool-for-enemies",
          "summary": "PressTV covers IRGC drone surveillance footage. Claims 'complete control' of Hormuz. Warns military vessels = ceasefire violation. Rezaei: 'major untouched levers.'"
        },
        {
          "name": "Xinhua/Iran",
          "headline": "Gaining Iran's trust sole way for U.S. to find exit from standoff",
          "timestamp": "2026-04-13T06:00:00Z",
          "url": "https://english.news.cn/20260413/5f5ba4e0213c4129b7b1e73ac8f497f7/c.html",
          "summary": "Xinhua covers Ghalibaf's post-talks statement: US failed to gain Iran's trust. Pezeshkian ready for 'balanced deal.' Iran framing: US caused failure."
        }
      ]
    }
  ]
}