{
  "lastUpdated": "2026-03-21T23:58:00Z",
  "updateFrequency": "at least 3x daily — morning, afternoon & evening PT",
  "donationUrl": "https://buymeacoffee.com/theossreport",
  "version": "3.0",
  "conflictDay": 22,
  "totalSocialPosts": 19,
  "dataFiles": {
    "events": 349,
    "warTimeline": 365,
    "breaking": 17,
    "socialPosts": 18,
    "governmentStatements": 179,
    "escalations": 157,
    "missileStrikes": 202,
    "damageLocations": 152,
    "factCheckClaims": 67,
    "statementsTimeline": 212,
    "damageData": 147,
    "factCheck": 70,
    "statements": 223,
    "globalInvolvement": 16,
    "timeline": 370
  },
  "updateNote": "Day 22 10:29 AM PDT refresh — IAEA confirms no radiation from Natanz 2nd strike; IDF 5 simultaneous ballistic missile storage strikes; Katz contradicts Trump wind-down; Pezeshkian Islamic Assembly proposal; Araghchi rejects ceasefire on NBC"
}